{
    "intents": [
        {
            "tag": "machine_failure_greetings",
            "patterns": [
                "Hello",
                "Hi",
                "Hey",
                "Greetings",
                "Good morning",
                "Good afternoon",
                "Good evening"
            ],
            "responses": [
                "Hello! I can help you understand machine failure classification and prevention methods. How can I assist you?",
                "Hi there! Need help with machine failure prevention? I'm here to guide you.",
                "Hey! Let's talk about machine failure types and how to prevent them.",
                "Greetings! How can I assist you with machine maintenance and failure prevention?",
                "Good morning! Interested in learning about machine failures? I'm here to help.",
                "Good afternoon! Let’s discuss ways to prevent machine breakdowns.",
                "Good evening! Have any questions about machine failures and their prevention?"
            ]
        },
        {
            "tag": "machine_failure_definition",
            "patterns": [
                "What is machine failure?",
                "Define machine failure",
                "Explain machine failure",
                "What causes machine failure?"
            ],
            "responses": [
                "Machine failure occurs when a system, component, or equipment stops functioning as expected, leading to operational disruptions.",
                "A machine failure is an unexpected breakdown of equipment due to wear, improper usage, or external factors.",
                "Machine failure happens when a machine can no longer perform its intended function due to mechanical, electrical, or operational faults."
            ]
        },
        {
            "tag": "machine_failure_causes",
            "patterns": [
                "What are the causes of machine failure?",
                "Why do machines fail?",
                "List some reasons for machine failure"
            ],
            "responses": [
                "Common causes of machine failure include poor maintenance, excessive load, overheating, power fluctuations, and wear and tear over time.",
                "Machines fail due to improper lubrication, material fatigue, overheating, and electrical failures.",
                "Failure can occur due to environmental factors, misuse, lack of regular inspections, and overloading."
            ]
        },
        {
            "tag": "machine_failure_prevention",
            "patterns": [
                "How can machine failure be prevented?",
                "What are some prevention methods for machine failure?",
                "How to avoid machine breakdown?"
            ],
            "responses": [
                "To prevent machine failure, conduct regular maintenance, use proper lubrication, monitor operational limits, and ensure a controlled working environment.",
                "Routine inspections, predictive maintenance, and proper usage training can help prevent machine failures.",
                "Preventative measures include monitoring machine conditions, avoiding overuse, and following manufacturer guidelines."
            ]
        },
        {
            "tag": "random_failure",
            "patterns": [
                "What is random failure?",
                "Explain random failure",
                "What causes random machine failure?"
            ],
            "responses": [
                "Random failure occurs unpredictably and is often caused by unexpected external factors like power surges, material defects, or sudden operational conditions.",
                "Random failures are difficult to anticipate and usually happen due to unforeseen mechanical or environmental issues.",
                "To minimize random failure, implement predictive maintenance and monitor machine performance closely."
            ]
        },
        {
            "tag": "random_failure_prevention",
            "patterns": [
                "How can I prevent random failure?",
                "What are the best ways to prevent random failures?",
                "How to reduce random machine failure?"
            ],
            "responses": [
                "To prevent random failure, conduct frequent equipment checks, use quality components, and install monitoring systems.",
                "Predictive analytics and condition-based maintenance can help reduce the chances of random failure.",
                "Ensuring environmental stability and using fail-safe mechanisms can help prevent unexpected machine failures."
            ]
        },
        {
            "tag": "tool_wear_failure",
            "patterns": [
                "What is tool wear failure?",
                "Explain tool wear failure",
                "Why does tool wear failure occur?"
            ],
            "responses": [
                "Tool wear failure occurs due to prolonged use of machine tools, leading to gradual degradation and reduced efficiency.",
                "This type of failure happens due to friction, heat, and material fatigue over time.",
                "Tool wear failure can be reduced by using high-quality materials, regular sharpening, and lubrication."
            ]
        },
        {
            "tag": "tool_wear_failure_prevention",
            "patterns": [
                "How can I prevent tool wear failure?",
                "What are the best ways to prevent tool wear?",
                "How to reduce tool wear failure?"
            ],
            "responses": [
                "Use high-quality cutting tools, apply proper lubrication, and replace worn-out tools regularly.",
                "Tool wear can be minimized by maintaining optimal operating conditions and avoiding excessive force on equipment.",
                "Regular inspections and tool material upgrades can significantly reduce wear-related failures."
            ]
        },
        {
            "tag": "power_failure",
            "patterns": [
                "What is power failure?",
                "Explain power failure in machines",
                "Why does power failure happen?"
            ],
            "responses": [
                "Power failure occurs when there is an electrical disruption, voltage instability, or unexpected power outage affecting machine operation.",
                "Machines experience power failure due to faulty wiring, overloaded circuits, or sudden electricity supply cuts.",
                "Installing power stabilizers and backup systems can prevent power-related failures."
            ]
        },
        {
            "tag": "power_failure_prevention",
            "patterns": [
                "How can I prevent power failure?",
                "What are the best ways to prevent power failures?",
                "How to reduce power failure risks?"
            ],
            "responses": [
                "Use an uninterruptible power supply (UPS) and voltage regulators to protect machines from power failures.",
                "Regularly inspect electrical components and maintain stable voltage inputs to prevent disruptions.",
                "Backup generators and surge protectors can help machines continue functioning during power failures."
            ]
        },
        {
            "tag": "heat_dissipation_failure",
            "patterns": [
                "What is heat dissipation failure?",
                "Explain heat dissipation failure",
                "Why does heat dissipation failure happen?"
            ],
            "responses": [
                "Heat dissipation failure occurs when a machine cannot effectively release heat, leading to overheating and potential breakdown.",
                "Poor ventilation, clogged cooling systems, and continuous high-load operations can cause heat dissipation failure.",
                "Proper cooling mechanisms, regular cleaning, and heat-resistant materials can help prevent heat issues."
            ]
        },
        {
            "tag": "heat_dissipation_failure_prevention",
            "patterns": [
                "How can I prevent heat dissipation failure?",
                "What are the best ways to prevent overheating?",
                "How to reduce heat dissipation failure?"
            ],
            "responses": [
                "Ensure proper ventilation, clean cooling fans regularly, and use high-quality thermal insulation materials.",
                "Heat dissipation can be improved by maintaining cooling systems and reducing machine load during peak performance.",
                "Installing temperature monitoring sensors and heat sinks can prevent overheating failures."
            ]
        },
        {
            "tag": "overstrain_failure",
            "patterns": [
                "What is overstrain failure?",
                "Explain overstrain failure",
                "Why does overstrain failure occur?"
            ],
            "responses": [
                "Overstrain failure occurs when a machine is subjected to excessive stress beyond its designed capacity, leading to damage or breakdown.",
                "Causes of overstrain failure include overloading, prolonged usage without rest, and improper usage of equipment.",
                "Proper workload distribution and stress analysis can help prevent machine overstrain failures."
            ]
        },
        {
            "tag": "overstrain_failure_prevention",
            "patterns": [
                "How can I prevent overstrain failure?",
                "What are the best ways to prevent overstrain?",
                "How to reduce overstrain failure?"
            ],
            "responses": [
                "Avoid exceeding machine load limits, provide regular rest periods, and use shock-absorbing materials.",
                "Monitoring strain levels and using automated alerts for excessive load can help prevent overstrain failures.",
                "Follow manufacturer guidelines for maximum load capacities to reduce overstrain risks."
            ]
        },
            {
      "tag": "power_failure_prevention",
      "patterns": [
        "How can I prevent power failure in machines?",
        "What measures can be taken to avoid power failure?",
        "How do I ensure consistent power for my machines?"
      ],
      "responses": [
        "To prevent power failure, ensure stable electrical connections, use surge protectors, and monitor voltage levels regularly. Routine electrical maintenance can also help to reduce the risk.",
        "Using voltage regulators, surge protectors, and regular inspection of power systems will help prevent power failure in machines."
      ]
    },
    {
      "tag": "heat_dissipation_failure_explanation",
      "patterns": [
        "What is heat dissipation failure?",
        "Why does heat dissipation failure occur?",
        "Can you explain heat dissipation failure in machines?"
      ],
      "responses": [
        "Heat dissipation failure happens when a machine cannot effectively release the heat it generates during operation, leading to overheating and potential breakdowns.",
        "When a machine generates more heat than it can dissipate, it may cause components to overheat, reducing the life span and efficiency of the machine. Proper cooling systems are crucial to prevent this."
      ]
    },
    {
      "tag": "heat_dissipation_failure_prevention",
      "patterns": [
        "How can I prevent heat dissipation failure?",
        "What can be done to improve heat dissipation in machines?",
        "How do I manage heat buildup in machines?"
      ],
      "responses": [
        "To prevent heat dissipation failure, ensure machines have proper cooling systems such as fans or heat exchangers. Regular maintenance of cooling components will help manage heat effectively.",
        "Maintaining proper airflow, cleaning cooling fans, and using high-quality heat-resistant materials can prevent heat dissipation failure."
      ]
    },
    {
      "tag": "overstrain_failure_explanation",
      "patterns": [
        "What is overstrain failure?",
        "Can you explain what overstrain failure is?",
        "Why does overstrain failure happen in machines?"
      ],
      "responses": [
        "Overstrain failure occurs when a machine is subjected to loads or stresses that exceed its design limits, leading to mechanical damage and breakdowns.",
        "When machines are overloaded beyond their capacity or experience excessive force, overstrain can lead to premature failure of components. Regular load checks and monitoring can prevent this."
      ]
    },
    {
      "tag": "overstrain_failure_prevention",
      "patterns": [
        "How can I prevent overstrain failure?",
        "What steps can be taken to avoid overstrain in machines?",
        "How do I manage machine loads to prevent overstrain?"
      ],
      "responses": [
        "To prevent overstrain failure, avoid exceeding the recommended load limits, perform regular load testing, and ensure proper machine calibration to handle the required stress.",
        "Establishing proper machine capacity and using load sensors can help monitor strain and prevent overloading, thus avoiding overstrain failure."
      ]
    },
    {
      "tag": "failure_detection_methods",
      "patterns": [
        "How can I detect machine failures before they happen?",
        "What are the best failure detection methods?",
        "Can you suggest ways to detect potential machine failures?"
      ],
      "responses": [
        "Failure detection methods include predictive maintenance tools like vibration analysis, thermal imaging, and regular inspections. Sensors can also help monitor machine conditions in real time.",
        "Using condition monitoring systems, analyzing vibration patterns, and applying advanced diagnostic tools such as ultrasonic sensors can help detect potential failures early."
      ]
    },
    {
      "tag": "preventive_maintenance",
      "patterns": [
        "What is preventive maintenance?",
        "How can I implement preventive maintenance for machines?",
        "Can you explain preventive maintenance for machines?"
      ],
      "responses": [
        "Preventive maintenance is the practice of performing regular checks and servicing on equipment to ensure it functions optimally and to prevent potential failures.",
        "Implementing preventive maintenance involves creating a schedule for inspections, cleaning, lubricating parts, and replacing worn components to extend the machine’s lifespan."
      ]
    },
    {
      "tag": "preventive_maintenance_schedule",
      "patterns": [
        "How do I create a preventive maintenance schedule?",
        "What should be included in a preventive maintenance schedule?",
        "Can you guide me on setting up a preventive maintenance plan?"
      ],
      "responses": [
        "A preventive maintenance schedule should include regular inspections, lubrication, cleaning, part replacements, and testing of machine components. Set a frequency based on usage and manufacturer recommendations.",
        "Create a schedule based on operating hours or a specific time interval for checking components. It should cover all critical parts and processes of the machine."
      ]
    },
    {
      "tag": "failure_analysis_tools",
      "patterns": [
        "What tools can I use for failure analysis?",
        "How can I perform a failure analysis on my machine?",
        "Can you recommend failure analysis tools?"
      ],
      "responses": [
        "Failure analysis tools include vibration analysis equipment, thermal cameras, ultrasonic testing devices, and software that can monitor machine health and predict failure risks.",
        "Tools like root cause analysis, fault tree analysis, and failure mode effects analysis (FMEA) can help identify potential failure points and improve maintenance strategies."
      ]
    },
    {
      "tag": "machine_lifetime_optimization",
      "patterns": [
        "How can I optimize machine lifetime?",
        "What methods can extend the life of my machine?",
        "Can you suggest ways to improve machine longevity?"
      ],
      "responses": [
        "Optimizing machine lifetime involves regular maintenance, avoiding overloading, using high-quality components, and monitoring machine conditions to prevent failures.",
        "To extend machine life, ensure proper lubrication, use parts designed for durability, and implement consistent preventive maintenance practices."
      ]
    },
    {
      "tag": "machine_performance_optimization",
      "patterns": [
        "How can I optimize the performance of my machines?",
        "What steps can improve machine performance?",
        "Can you suggest performance optimization techniques?"
      ],
      "responses": [
        "Optimizing machine performance involves regular cleaning, ensuring all parts are functioning correctly, fine-tuning operating conditions, and replacing worn-out components.",
        "Improve machine performance by adjusting parameters, using high-quality materials, and implementing automation for precision and consistency."
      ]
    },
    {
      "tag": "machine_failure_categorization",
      "patterns": [
        "How do I categorize machine failures?",
        "What are the categories of machine failure?",
        "Can you explain the classification of machine failures?"
      ],
      "responses": [
        "Machine failures can be categorized into different types, such as mechanical, electrical, thermal, and operational failures. Each category may require different preventive strategies.",
        "Categorizing machine failures helps identify the root causes and implement the appropriate maintenance and repair solutions. Common categories include electrical, mechanical, and human-related failures."
      ]
    },
    {
      "tag": "heat_dissipation_failure_cause",
      "patterns": [
        "What causes heat dissipation failure?",
        "Why does heat dissipation fail in machines?",
        "What are the reasons for heat dissipation issues in machines?"
      ],
      "responses": [
        "Heat dissipation failure typically occurs when a machine's cooling system is inefficient, or airflow is obstructed, leading to excess heat buildup.",
        "Common causes include clogged cooling vents, malfunctioning fans, low coolant levels, and excessive operating conditions that generate more heat than the system can handle."
      ]
    },
    {
      "tag": "machine_overload_prevention",
      "patterns": [
        "How can I prevent machine overload?",
        "What can be done to avoid overloading machines?",
        "How do I ensure that my machine is not overloaded?"
      ],
      "responses": [
        "To prevent overload, always operate machines within their specified capacity, regularly monitor performance, and install load sensors to detect excessive strain.",
        "Prevent overload by training operators on machine limits, using automatic load control systems, and regularly inspecting machine load-bearing components."
      ]
    },
    {
      "tag": "machine_failure_symptoms",
      "patterns": [
        "What are the symptoms of a machine failure?",
        "How do I know if my machine is about to fail?",
        "What signs indicate machine failure?"
      ],
      "responses": [
        "Symptoms of machine failure include unusual sounds, vibrations, overheating, power loss, and unexpected shutdowns. Monitoring these symptoms can help prevent further damage.",
        "Watch for early warning signs like increased energy consumption, overheating, or abnormal sounds. Regular diagnostics can help catch issues early before a failure occurs."
      ]
    },
    {
      "tag": "failure_risk_assessment",
      "patterns": [
        "How do I assess failure risk in my machine?",
        "What factors should I consider in a failure risk assessment?",
        "Can you guide me on assessing machine failure risk?"
      ],
      "responses": [
        "To assess failure risk, consider factors such as machine age, usage frequency, maintenance history, and operating environment. Conducting a risk analysis regularly can help identify vulnerabilities.",
        "Perform a risk assessment by evaluating machine components, assessing environmental conditions, and tracking failure history to predict potential failures."
      ]
    },
        {
      "tag": "vibration_failure_explanation",
      "patterns": [
        "What is vibration failure?",
        "How does vibration cause failure in machines?",
        "Can vibration lead to machine failure?"
      ],
      "responses": [
        "Vibration failure occurs when a machine or its components experience excessive vibrations, leading to wear and tear on bearings, shafts, and other parts.",
        "Excessive vibration can lead to imbalanced components, causing misalignment and damage over time, which could ultimately cause machine failure."
      ]
    },
    {
      "tag": "vibration_failure_prevention",
      "patterns": [
        "How can I prevent vibration failure?",
        "What can I do to reduce vibrations in my machine?",
        "How do I control vibration issues in machines?"
      ],
      "responses": [
        "To prevent vibration failure, ensure all parts are properly balanced, use vibration dampeners, and regularly inspect bearings and other components for wear.",
        "Proper alignment, balancing, and regular inspection of key machine components will help reduce the risk of vibration failure."
      ]
    },
    {
      "tag": "oil_leak_failure_explanation",
      "patterns": [
        "What causes oil leak failure?",
        "Can oil leakage lead to machine failure?",
        "What happens when there’s an oil leak in a machine?"
      ],
      "responses": [
        "Oil leak failure occurs when a machine’s lubrication system fails, leading to a loss of oil and inadequate lubrication of critical components.",
        "Oil leakage can cause components to overheat and wear out due to insufficient lubrication, which may result in machine failure."
      ]
    },
    {
      "tag": "oil_leak_failure_prevention",
      "patterns": [
        "How can I prevent oil leaks in machines?",
        "What are the best ways to avoid oil leakage?",
        "How do I ensure no oil leaks in my machine?"
      ],
      "responses": [
        "Regularly check seals, gaskets, and hoses for wear, and replace damaged components immediately. Use high-quality lubricants that are less likely to cause leakage.",
        "Prevent oil leaks by maintaining good seals, monitoring oil levels, and scheduling routine inspections to detect any issues early."
      ]
    },
    {
      "tag": "electrical_failure_explanation",
      "patterns": [
        "What causes electrical failure in machines?",
        "How does electrical failure affect machines?",
        "What is the impact of electrical failure on machines?"
      ],
      "responses": [
        "Electrical failure happens when there is a disruption in the machine’s power supply, often caused by faulty wiring, malfunctioning circuits, or power surges.",
        "Electrical failures can cause machines to stop working entirely or operate inefficiently. Common causes include damaged wiring, short circuits, and power fluctuations."
      ]
    },
    {
      "tag": "electrical_failure_prevention",
      "patterns": [
        "How can I prevent electrical failure in machines?",
        "What should I do to avoid electrical failure?",
        "How do I prevent electrical issues in my machines?"
      ],
      "responses": [
        "Ensure proper grounding of electrical components, use surge protectors, and schedule regular checks on wiring and circuit boards.",
        "To prevent electrical failure, inspect electrical components regularly, protect circuits from surges, and replace any worn-out cables or connections."
      ]
    },
    {
      "tag": "bearing_failure_explanation",
      "patterns": [
        "What causes bearing failure?",
        "How does bearing failure occur in machines?",
        "Can you explain bearing failure in machinery?"
      ],
      "responses": [
        "Bearing failure occurs when bearings become worn out due to excessive load, lack of lubrication, or contamination from dirt or moisture.",
        "Common causes of bearing failure include improper lubrication, excessive heat, and contamination, which lead to friction and eventual breakdown of the bearings."
      ]
    },
    {
      "tag": "bearing_failure_prevention",
      "patterns": [
        "How can I prevent bearing failure?",
        "What are the ways to avoid bearing failure?",
        "How do I maintain bearings to avoid failure?"
      ],
      "responses": [
        "Prevent bearing failure by ensuring proper lubrication, regularly inspecting for wear and tear, and cleaning them from contaminants.",
        "Regular maintenance such as lubricating bearings, checking alignment, and ensuring they’re free of contaminants can significantly extend bearing life."
      ]
    },
    {
      "tag": "corrosion_failure_explanation",
      "patterns": [
        "What is corrosion failure?",
        "How does corrosion cause machine failure?",
        "Why does corrosion cause damage to machines?"
      ],
      "responses": [
        "Corrosion failure occurs when metal parts of a machine deteriorate due to exposure to moisture, chemicals, or extreme temperatures.",
        "Corrosion leads to material degradation, making parts weaker and prone to cracking or breaking, which can cause machine failure."
      ]
    },
    {
      "tag": "corrosion_failure_prevention",
      "patterns": [
        "How can I prevent corrosion failure?",
        "What can be done to avoid corrosion in machines?",
        "How do I stop machines from corroding?"
      ],
      "responses": [
        "To prevent corrosion, ensure machines are properly sealed, avoid exposure to moisture, and use corrosion-resistant materials or coatings.",
        "Applying protective coatings, maintaining dry conditions, and using rust inhibitors can effectively prevent corrosion and extend machine life."
      ]
    },
    {
      "tag": "cooling_system_failure_explanation",
      "patterns": [
        "What is cooling system failure?",
        "How does a cooling system failure affect machines?",
        "What causes cooling system failure in machines?"
      ],
      "responses": [
        "Cooling system failure occurs when the cooling mechanism (such as fans, heat exchangers, or pumps) becomes ineffective, causing the machine to overheat.",
        "Overheating can cause significant damage to internal components, leading to reduced efficiency, malfunction, or complete failure of the machine."
      ]
    },
    {
      "tag": "cooling_system_failure_prevention",
      "patterns": [
        "How can I prevent cooling system failure?",
        "What should I do to avoid cooling system failure?",
        "How do I maintain cooling systems in machines?"
      ],
      "responses": [
        "Prevent cooling system failure by regularly cleaning heat exchangers, ensuring proper coolant levels, and monitoring temperature gauges.",
        "Ensure regular maintenance of cooling systems, including cleaning vents, replacing faulty fans, and checking coolant levels to prevent overheating."
      ]
    },
    {
      "tag": "air_filter_failure_explanation",
      "patterns": [
        "What is air filter failure?",
        "How does air filter failure occur?",
        "What causes air filter failure in machines?"
      ],
      "responses": [
        "Air filter failure happens when filters become clogged or damaged, preventing proper airflow and causing inefficiency in machine operations.",
        "Dirty or damaged air filters reduce airflow, leading to overheating, reduced efficiency, and potential damage to internal components."
      ]
    },
    {
      "tag": "air_filter_failure_prevention",
      "patterns": [
        "How can I prevent air filter failure?",
        "What can be done to avoid air filter failure?",
        "How do I maintain air filters in machines?"
      ],
      "responses": [
        "Regularly clean or replace air filters, monitor airflow, and ensure the filters are free of obstructions to avoid failure.",
        "Prevent air filter failure by maintaining a regular cleaning schedule and replacing them as needed to ensure proper airflow and machine performance."
      ]
    },
    {
      "tag": "software_failure_explanation",
      "patterns": [
        "What causes software failure in machines?",
        "How does software failure affect machines?",
        "Can software failure lead to machine breakdown?"
      ],
      "responses": [
        "Software failure can occur due to bugs, improper coding, or conflicts with hardware, leading to malfunction or improper operation of the machine.",
        "Software issues can cause machines to operate erratically, leading to incorrect readings, system crashes, or even physical damage to the machine."
      ]
    },
    {
      "tag": "software_failure_prevention",
      "patterns": [
        "How can I prevent software failure in machines?",
        "What steps can I take to avoid software issues?",
        "How do I ensure my machine software runs smoothly?"
      ],
      "responses": [
        "To prevent software failure, ensure regular updates, perform stress testing, and monitor software for bugs or vulnerabilities.",
        "Keeping software up-to-date, testing for bugs, and ensuring compatibility with hardware are key steps in preventing software failure."
      ]
    },
    {
      "tag": "maintenance_cost_reduction",
      "patterns": [
        "How can I reduce machine maintenance costs?",
        "What are some ways to cut down on maintenance expenses?",
        "Can you suggest methods for reducing maintenance costs?"
      ],
      "responses": [
        "Reduce maintenance costs by focusing on preventive maintenance, using high-quality parts, and implementing predictive maintenance to avoid costly repairs.",
        "To reduce costs, prioritize preventive maintenance, extend the life of equipment with proper care, and use technology to monitor machine health."
      ]
    },
    {
      "tag": "supply_chain_failure_explanation",
      "patterns": [
        "What causes supply chain failure in machines?",
        "How does supply chain failure affect machine operations?",
        "Can supply chain issues lead to machine failure?"
      ],
      "responses": [
        "Supply chain failure can occur when critical parts or materials are delayed or unavailable, disrupting production schedules and causing machine downtime.",
        "Delays in the supply chain can prevent machines from being repaired or maintained on time, leading to potential failures or inefficient operations."
      ]
    },
    {
      "tag": "supply_chain_failure_prevention",
      "patterns": [
        "How can I prevent supply chain failure in machine maintenance?",
        "What can be done to avoid supply chain issues?",
        "How do I ensure a reliable supply chain for machine parts?"
      ],
      "responses": [
        "Maintain strong relationships with suppliers, monitor inventory levels, and have backup suppliers to avoid supply chain disruptions.",
        "Prevent supply chain failures by having contingency plans, forecasting needs accurately, and ensuring timely deliveries of critical parts."
      ]
    }
    ]
}
